setup.py
hand/__init__.py
hand/baserss.py
hand.egg-info/PKG-INFO
hand.egg-info/SOURCES.txt
hand.egg-info/dependency_links.txt
hand.egg-info/not-zip-safe
hand.egg-info/requires.txt
hand.egg-info/top_level.txt