Metadata-Version: 1.0
Name: hand
Version: 0.5
Summary: Feed generator for screen scrapers
Home-page: http://github.com/luizirber/hand
Author: Luiz Irber
Author-email: luiz.irber@gmail.com
License: GPLv3
Platform: UNKNOWN
Classifier: Development Status :: 4 - Beta
Classifier: Environment :: Console
Classifier: Intended Audience :: Developers
Classifier: License :: OSI Approved :: GNU General Public License (GPL)
Classifier: Operating System :: OS Independent
Classifier: Topic :: Text Processing :: Markup :: XML
